goesnex_cli_package/__init__.py
goesnex_cli_package/helper.py
goesnex_cli_package/main.py
goesnex_cli_package-0.0.2.dist-info/METADATA
goesnex_cli_package-0.0.2.dist-info/WHEEL
goesnex_cli_package-0.0.2.dist-info/entry_points.txt
goesnex_cli_package-0.0.2.dist-info/top_level.txt
goesnex_cli_package-0.0.2.dist-info/RECORD
